stripe_dash/StripeDash.py
stripe_dash/__init__.py
stripe_dash/_imports_.py
stripe_dash/metadata.json
stripe_dash/package-info.json
stripe_dash/stripe_dash.min.js
stripe_dash/stripe_dash.min.js.map
stripe_dash-0.0.3.dist-info/LICENSE
stripe_dash-0.0.3.dist-info/METADATA
stripe_dash-0.0.3.dist-info/WHEEL
stripe_dash-0.0.3.dist-info/top_level.txt
stripe_dash-0.0.3.dist-info/RECORD
