Metadata-Version: 2.1
Name: stripe_dash
Version: 0.0.3
Summary: stripe dash compoenent
Author: tony carnevale <datasciencetony@gmail.com>
License: MIT
Classifier: Framework :: Dash
License-File: LICENSE
